pycolor/__init__.py
pycolor/pycolor_main2.py
pycolor3-0.0.5.dist-info/LICENSE
pycolor3-0.0.5.dist-info/METADATA
pycolor3-0.0.5.dist-info/WHEEL
pycolor3-0.0.5.dist-info/top_level.txt
pycolor3-0.0.5.dist-info/RECORD
