Metadata-Version: 2.1
Name: pycolor3
Version: 0.0.5
Summary: Color Markup In Python!
Home-page: https://github.com/0Exe/pycolor
Author: 0Exe
Author-email: zeroexe3000@gmail.com
License: UNKNOWN
Project-URL: Bug Tracker, https://github.com/0Exe/pycolor/issues
Platform: UNKNOWN
Classifier: Programming Language :: Python :: 3
Classifier: License :: OSI Approved :: MIT License
Classifier: Operating System :: OS Independent
Requires-Python: >=3.6
License-File: LICENSE
